qodex_recognition/__init__.py
qodex_recognition/main.py
qodex_recognition/tests/__init__.py
qodex_recognition/tests/main_tests.py
qodex_recognition-0.1.54.dist-info/licenses/LICENSE
qodex_recognition-0.1.54.dist-info/METADATA
qodex_recognition-0.1.54.dist-info/WHEEL
qodex_recognition-0.1.54.dist-info/top_level.txt
qodex_recognition-0.1.54.dist-info/RECORD
